pylz78/__init__.py
pylz78/__main__.py
pylz78/compression/__init__.py
pylz78/ctrie/__init__.py
pylz78/ctrie/trie.py
pylz78-0.1.0.dist-info/LICENSE
pylz78-0.1.0.dist-info/METADATA
pylz78-0.1.0.dist-info/WHEEL
pylz78-0.1.0.dist-info/entry_points.txt
pylz78-0.1.0.dist-info/top_level.txt
pylz78-0.1.0.dist-info/RECORD
