Metadata-Version: 2.1
Name: pylz78
Version: 0.1.0
Summary: lz78 compressor in python
Home-page: https://github.com/ptcar2009/ALG2-TP1
Author: Pedro Carvalho
Author-email: ptcar@pteco.dev
License: UNKNOWN
Platform: UNKNOWN
Classifier: Programming Language :: Python :: 3
Classifier: License :: OSI Approved :: MIT License
Classifier: Operating System :: OS Independent
Requires-Python: >=3.6
